amplitf/__init__.py
amplitf/dynamics.py
amplitf/interface.py
amplitf/kinematics.py
amplitf/likelihood.py
amplitf/optimisation.py
amplitf/toymc.py
amplitf/phasespace/__init__.py
amplitf/phasespace/baryonic_3body_phasespace.py
amplitf/phasespace/combined_phasespace.py
amplitf/phasespace/dalitz_phasespace.py
amplitf/phasespace/four_body_angular_phasespace.py
amplitf/phasespace/four_body_helicity_phasespace.py
amplitf/phasespace/lambda_phasespace.py
amplitf/phasespace/rectangular_phasespace.py
amplitf/phasespace/veto_phasespace.py
amplitf-0.0a0.dist-info/METADATA
amplitf-0.0a0.dist-info/WHEEL
amplitf-0.0a0.dist-info/top_level.txt
amplitf-0.0a0.dist-info/RECORD
