Metadata-Version: 2.1
Name: amplitf
Version: 0.0a0
Summary: UNKNOWN
Home-page: https://github.com/apoluekt/AmpliTF
Author: Anton Poluektov
License: UNKNOWN
Platform: UNKNOWN
Requires-Python: >=3.5
Requires-Dist: iminuit
Requires-Dist: numpy
Requires-Dist: sympy
Requires-Dist: tensorflow (>=2.0)
